xypath/__init__.py
xypath/loader.py
xypath/matchers.py
xypath/xypath.py
xypath/xyzzy.py
xypath/contrib/__init__.py
xypath/contrib/excel.py
xypath/extern/__init__.py
xypath/extern/tabulate.py
xypath-1.1.1.dist-info/METADATA
xypath-1.1.1.dist-info/RECORD
xypath-1.1.1.dist-info/WHEEL
xypath-1.1.1.dist-info/entry_points.txt
xypath-1.1.1.dist-info/namespace_packages.txt
xypath-1.1.1.dist-info/top_level.txt
