Metadata-Version: 2.1
Name: xypath
Version: 1.1.1
Summary: Extract fields from tabular data with complex expressions.
Home-page: http://sensiblecode.io
Author: The Sensible Code Company Ltd
Author-email: feedback@sensiblecode.io
License: BSD
Platform: UNKNOWN
Classifier: Development Status :: 3 - Alpha
Classifier: Intended Audience :: Developers
Classifier: License :: OSI Approved :: BSD License
Classifier: Operating System :: POSIX :: Linux
Classifier: Operating System :: Microsoft :: Windows
Classifier: Programming Language :: Python :: 2.7
Classifier: Programming Language :: Python :: 3.4
Classifier: Programming Language :: Python :: 3.5
Classifier: Programming Language :: Python :: 3.6
Requires-Dist: messytables (==0.15.1)
